<?xml version="1.0" ?>
<stations>
    <station name="Val-Vert">
        <line description="Renens-14 Avril - Val-Vert" id="11821953316814881" name="7">
            <journey from="Renens-14 Avril" id="2533279085378439" internalDescription="R-14A &gt; VVERT" name="Renens-14 Avril &gt; Val-Vert" to="Val-Vert"/>
            <journey from="Val-Vert" id="2533279085378448" internalDescription="VVERT &gt; R-14A" name="Val-Vert &gt; Renens-14 Avril" to="Renens-14 Avril"/>
        </line>
        <line description="Pully-Port - Grandvaux-Pra Grana" id="11821953316814870" name="47">
            <journey from="Pully-Port" id="2533279085381389" internalDescription="PPORT &gt; GRAVX" name="Pully-Port &gt; Grandvaux" to="Grandvaux"/>
            <journey from="Grandvaux" id="2533279085384514" internalDescription="GRAVX &gt; PPORT" name="Grandvaux &gt; Pully-Port" to="Pully-Port"/>
        </line>
        <line description="Pully-Clergère - Daillettes" id="11821953316814871" name="48">
            <journey from="Daillettes" id="2533279085383047" internalDescription="DTTES &gt; CLERG" name="Daillettes &gt; Pully-Clergère" to="Pully-Clergère"/>
        </line>
        <line description="Montbenon - Grandvaux-Pra Grana" id="11821953316814878" name="66">
            <journey from="Montbenon" id="2533279085363738" internalDescription="MBNON &gt; GRAVX" name="Montbenon &gt; Grandvaux" to="Grandvaux"/>
            <journey from="Grandvaux" id="2533279085363750" internalDescription="GRAVX &gt; MBNON" name="Grandvaux &gt; Montbenon" to="Montbenon"/>
        </line>
    </station>
    <station name="Valency">
        <line description="Lutry-Corniche - Prilly-Eglise" id="11821953316814886" name="9">
            <journey from="Lutry-Corniche" id="2533279085378570" internalDescription="LUTRY &gt; PRY" name="Lutry-Corniche &gt; Prilly-Eglise" to="Prilly-Eglise"/>
            <journey from="Prilly-Eglise" id="2533279085378585" internalDescription="PRY &gt; LUTRY" name="Prilly-Eglise &gt; Lutry-Corniche" to="Lutry-Corniche"/>
        </line>
    </station>
    <station name="Valentin">
        <line description="Maladière - Blécherette" id="11821953316814849" name="1">
            <journey from="Maladière" id="2533279085378050" internalDescription="MALAD &gt; BLECH" name="Maladière &gt; Blécherette" to="Blécherette"/>
            <journey from="Blécherette" id="2533279085378063" internalDescription="BLECH &gt; MALAD" name="Blécherette &gt; Maladière" to="Maladière"/>
        </line>
        <line description="Maladière - Désert" id="11821953316814855" name="2">
            <journey from="Maladière-Lac" id="2533279085378143" internalDescription="MALAD &gt; DST" name="Maladière-Lac &gt; Désert" to="Désert"/>
            <journey from="Désert" id="2533279085378157" internalDescription="DST &gt; MALAD" name="Désert &gt; Maladière-Lac" to="Maladière-Lac"/>
        </line>
    </station>
    <station name="Vallon">
        <line description="Pully-Port - Grandvaux-Pra Grana" id="11821953316814870" name="47">
            <journey from="Pully-Port" id="2533279085381389" internalDescription="PPORT &gt; GRAVX" name="Pully-Port &gt; Grandvaux" to="Grandvaux"/>
            <journey from="Grandvaux" id="2533279085384514" internalDescription="GRAVX &gt; PPORT" name="Grandvaux &gt; Pully-Port" to="Pully-Port"/>
        </line>
    </station>
    <station name="Vallonnette">
        <line description="Maladière - Sallaz" id="11821953316814873" name="6">
            <journey from="Maladière" id="2533279085378354" internalDescription="MALAD &gt; VALMT" name="Maladière &gt; Valmont" to="Valmont"/>
            <journey from="Valmont" id="2533279085378368" internalDescription="VALMT &gt; MALAD" name="Valmont &gt; Maladière" to="Maladière"/>
        </line>
    </station>
    <station name="Valmont">
        <line description="Maladière - Sallaz" id="11821953316814873" name="6">
            <journey from="Maladière" id="2533279085378354" internalDescription="MALAD &gt; VALMT" name="Maladière &gt; Valmont" to="Valmont"/>
            <journey from="Valmont" id="2533279085378368" internalDescription="VALMT &gt; MALAD" name="Valmont &gt; Maladière" to="Maladière"/>
        </line>
        <line description="Montolieu - Praz-Séchaud" id="11821953316814866" name="41">
            <journey from="Montolieu" id="2533279085378299" internalDescription="MONTO &gt; PSECH" name="Montolieu &gt; Praz-Séchaud" to="Praz-Séchaud"/>
            <journey from="Praz-Séchaud" id="2533279085378305" internalDescription="PSECH &gt; MONTO" name="Praz-Séchaud &gt; Montolieu" to="Montolieu"/>
        </line>
        <line description="Sallaz - Servion-Poste" id="11821953316814877" name="65">
            <journey from="Sallaz" id="2533279085363722" internalDescription="SALA &gt; SERV" name="Sallaz &gt; Servion-Poste" to="Servion-Poste"/>
            <journey from="Servion-Poste" id="2533279085363728" internalDescription="SERV &gt; SALA" name="Servion-Poste &gt; Sallaz" to="Sallaz"/>
        </line>
    </station>
    <station name="Veilloud">
        <line description="Venoge nord - Mont-Goulin" id="11821953316814862" name="33">
            <journey from="Venoge nord" id="2533279085403196" internalDescription="VENON &gt; MGOUL" name="Venoge nord &gt; Mont-Goulin" to="Mont-Goulin"/>
            <journey from="Mont-Goulin" id="2533279085403198" internalDescription="MGOUL &gt; VENON" name="Mont-Goulin &gt; Venoge nord" to="Venoge nord"/>
        </line>
    </station>
    <station name="Vennes">
        <line description="Ouchy - Croisettes" id="11821953316814890" name="m2">
            <journey from="Ouchy" id="2533279085382733" internalDescription="533" name="Ouchy &gt; Croisettes" to="Croisettes"/>
            <journey from="Croisettes" id="2533279085405911" internalDescription="285" name="Croisettes &gt; Ouchy" to="Ouchy"/>
        </line>
    </station>
    <station name="Venoge nord">
        <line description="Venoge nord - Mont-Goulin" id="11821953316814862" name="33">
            <journey from="Venoge nord" id="2533279085403196" internalDescription="VENON &gt; MGOUL" name="Venoge nord &gt; Mont-Goulin" to="Mont-Goulin"/>
            <journey from="Mont-Goulin" id="2533279085403198" internalDescription="MGOUL &gt; VENON" name="Mont-Goulin &gt; Venoge nord" to="Venoge nord"/>
        </line>
    </station>
    <station name="Venoge sud">
        <line description="Venoge sud - Renens-Gare sud" id="11821953316814895" name="31">
            <journey from="Venoge sud" id="2533279085403172" internalDescription="VENOS &gt; RCFFS" name="Venoge sud &gt; Renens-Gare sud" to="Renens-Gare sud"/>
            <journey from="Renens-Gare sud" id="2533279085403174" internalDescription="RCFFS &gt; VENOS" name="Renens-Gare sud &gt; Venoge sud" to="Venoge sud"/>
        </line>
    </station>
    <station name="Verdeil">
        <line description="Provence Nord - Verdeil" id="11821953316814851" name="13">
            <journey from="Provence Nord" id="2533279085378091" internalDescription="PROVN &gt; VDEIL" name="Provence Nord &gt; Verdeil" to="Verdeil"/>
            <journey from="Verdeil" id="2533279085378099" internalDescription="VDEIL &gt; PROVN" name="Verdeil &gt; Provence Nord" to="Provence Nord"/>
        </line>
    </station>
    <station name="Verger">
        <line description="Croisettes - Moudon-Gare" id="11821953316814875" name="62">
            <journey from="Croisettes" id="2533279085363696" internalDescription="CROIS &gt; MOUD" name="Croisettes &gt; Moudon-Gare" to="Moudon-Gare"/>
            <journey from="Croisettes" id="2533279085363699" internalDescription="CROIS &gt; MOUD    via La Râpe" name="Croisettes &gt; Moudon-Gare" to="Moudon-Gare"/>
            <journey from="Moudon-Gare" id="2533279085363707" internalDescription="MOUD &gt; CROIS    via La Râpe" name="Moudon-Gare &gt; Croisettes" to="Croisettes"/>
            <journey from="Moudon-Gare" id="2533279085379036" internalDescription="MOUD &gt; CROIS" name="Moudon-Gare &gt; Croisettes" to="Croisettes"/>
        </line>
    </station>
    <station name="Verney">
        <line description="Verrière - Grand-Mont" id="11821953316814885" name="8">
            <journey from="Verrière" id="2533279085378531" internalDescription="VERRI &gt; GMONT" name="Verrière &gt; Grand-Mont" to="Grand-Mont"/>
            <journey from="Grand-Mont" id="2533279085378551" internalDescription="GMONT &gt; VERRI" name="Grand-Mont &gt; Verrière" to="Verrière"/>
        </line>
    </station>
    <station name="Verrière">
        <line description="Verrière - Grand-Mont" id="11821953316814885" name="8">
            <journey from="Verrière" id="2533279085378531" internalDescription="VERRI &gt; GMONT" name="Verrière &gt; Grand-Mont" to="Grand-Mont"/>
            <journey from="Grand-Mont" id="2533279085378551" internalDescription="GMONT &gt; VERRI" name="Grand-Mont &gt; Verrière" to="Verrière"/>
        </line>
    </station>
    <station name="Vers-chez-Blanc">
        <line description="Croisettes - Chalet-à-Gobet" id="11821953316814876" name="64">
            <journey from="Croisettes" id="2533279085363711" internalDescription="CROIS &gt; CHT" name="Croisettes &gt; Chalet-à-Gobet" to="Chalet-à-Gobet"/>
            <journey from="Chalet-à-Gobet" id="2533279085363716" internalDescription="CHT &gt; CROIS" name="Chalet-à-Gobet &gt; Croisettes" to="Croisettes"/>
        </line>
    </station>
    <station name="Vert-Bois">
        <line description="Croisettes - Moudon-Gare" id="11821953316814875" name="62">
            <journey from="Croisettes" id="2533279085363696" internalDescription="CROIS &gt; MOUD" name="Croisettes &gt; Moudon-Gare" to="Moudon-Gare"/>
            <journey from="Croisettes" id="2533279085363699" internalDescription="CROIS &gt; MOUD    via La Râpe" name="Croisettes &gt; Moudon-Gare" to="Moudon-Gare"/>
            <journey from="Moudon-Gare" id="2533279085363707" internalDescription="MOUD &gt; CROIS    via La Râpe" name="Moudon-Gare &gt; Croisettes" to="Croisettes"/>
            <journey from="Moudon-Gare" id="2533279085379036" internalDescription="MOUD &gt; CROIS" name="Moudon-Gare &gt; Croisettes" to="Croisettes"/>
        </line>
    </station>
    <station name="Victor-Ruffy">
        <line description="Maladière - Sallaz" id="11821953316814873" name="6">
            <journey from="Maladière" id="2533279085378354" internalDescription="MALAD &gt; VALMT" name="Maladière &gt; Valmont" to="Valmont"/>
            <journey from="Valmont" id="2533279085378368" internalDescription="VALMT &gt; MALAD" name="Valmont &gt; Maladière" to="Maladière"/>
        </line>
    </station>
    <station name="Vieux-Moulin">
        <line description="Lausanne-Gare - Bellevaux" id="11821953316814859" name="3">
            <journey from="Bellevaux" id="2533279085378225" internalDescription="BELVO &gt; GARE" name="Bellevaux &gt; Lausanne-Gare" to="Lausanne-Gare"/>
        </line>
        <line description="Verrière - Grand-Mont" id="11821953316814885" name="8">
            <journey from="Verrière" id="2533279085378531" internalDescription="VERRI &gt; GMONT" name="Verrière &gt; Grand-Mont" to="Grand-Mont"/>
            <journey from="Grand-Mont" id="2533279085378551" internalDescription="GMONT &gt; VERRI" name="Grand-Mont &gt; Verrière" to="Verrière"/>
        </line>
        <line description="Montbenon - Grand Vennes" id="11821953316814852" name="16">
            <journey from="Grand Vennes" id="2533279085363286" internalDescription="GVENN &gt; MBNON" name="Grand Vennes &gt; Montbenon" to="Montbenon"/>
        </line>
        <line description="Lausanne-Flon - Clochatte" id="11821953316814857" name="22">
            <journey from="Lausanne-Flon" id="2533279085378190" internalDescription="FLON &gt; CLOCH" name="Lausanne-Flon &gt; Clochatte" to="Clochatte"/>
            <journey from="Clochatte" id="2533279085378197" internalDescription="CLOCH &gt; FLON" name="Clochatte &gt; Lausanne-Flon" to="Lausanne-Flon"/>
        </line>
        <line description="Lausanne-Flon - Froideville-Laiterie" id="11821953316814874" name="60">
            <journey from="Laiterie" id="2533279085377482" internalDescription="FROIL &gt; FLON    via Bottens" name="Laiterie &gt; Lausanne-Flon" to="Lausanne-Flon"/>
            <journey from="Lausanne-Flon" id="2533279085377483" internalDescription="FLON &gt; FROIL    via Bottens" name="Lausanne-Flon &gt; Laiterie" to="Laiterie"/>
            <journey from="Lausanne-Flon" id="2533279085377486" internalDescription="FLON &gt; FROIL    via Montheron" name="Lausanne-Flon &gt; Laiterie" to="Laiterie"/>
            <journey from="Laiterie" id="2533279085377487" internalDescription="FROIL &gt; FLON    via Montheron" name="Laiterie &gt; Lausanne-Flon" to="Lausanne-Flon"/>
        </line>
    </station>
    <station name="Vigie">
        <line description="Renens-Gare - Lausanne-Flon" id="11821953316814882" name="m1">
            <journey from="Renens-Gare" id="2533279085363796" internalDescription="R-CFF &gt; FLON" name="Renens-Gare &gt; Lausanne-Flon" to="Lausanne-Flon"/>
            <journey from="Lausanne-Flon" id="2533279085363804" internalDescription="FLON &gt; R-CFF" name="Lausanne-Flon &gt; Renens-Gare" to="Renens-Gare"/>
        </line>
    </station>
    <station name="Vignes">
        <line description="Verrière - Grand-Mont" id="11821953316814885" name="8">
            <journey from="Verrière" id="2533279085378531" internalDescription="VERRI &gt; GMONT" name="Verrière &gt; Grand-Mont" to="Grand-Mont"/>
            <journey from="Grand-Mont" id="2533279085378551" internalDescription="GMONT &gt; VERRI" name="Grand-Mont &gt; Verrière" to="Verrière"/>
        </line>
    </station>
    <station name="Village">
        <line description="Lausanne-Flon - Froideville-Laiterie" id="11821953316814874" name="60">
            <journey from="Laiterie" id="2533279085377482" internalDescription="FROIL &gt; FLON    via Bottens" name="Laiterie &gt; Lausanne-Flon" to="Lausanne-Flon"/>
            <journey from="Lausanne-Flon" id="2533279085377483" internalDescription="FLON &gt; FROIL    via Bottens" name="Lausanne-Flon &gt; Laiterie" to="Laiterie"/>
            <journey from="Lausanne-Flon" id="2533279085377486" internalDescription="FLON &gt; FROIL    via Montheron" name="Lausanne-Flon &gt; Laiterie" to="Laiterie"/>
            <journey from="Laiterie" id="2533279085377487" internalDescription="FROIL &gt; FLON    via Montheron" name="Laiterie &gt; Lausanne-Flon" to="Lausanne-Flon"/>
        </line>
    </station>
    <station name="Villard">
        <line description="Lausanne-Gare - Bellevaux" id="11821953316814859" name="3">
            <journey from="Lausanne-Gare" id="2533279085378218" internalDescription="GARE &gt; BELVO" name="Lausanne-Gare &gt; Bellevaux" to="Bellevaux"/>
            <journey from="Bellevaux" id="2533279085378225" internalDescription="BELVO &gt; GARE" name="Bellevaux &gt; Lausanne-Gare" to="Lausanne-Gare"/>
        </line>
        <line description="Lausanne Gare - Blécherette" id="11821953316814856" name="21">
            <journey from="Lausanne-Gare" id="2533279085363369" internalDescription="GARE &gt; BLECH" name="Lausanne-Gare &gt; Blécherette" to="Blécherette"/>
            <journey from="Blécherette" id="2533279085363380" internalDescription="BLECH &gt; GARE" name="Blécherette &gt; Lausanne-Gare" to="Lausanne-Gare"/>
        </line>
    </station>
    <station name="Villars">
        <line description="Venoge nord - Mont-Goulin" id="11821953316814862" name="33">
            <journey from="Venoge nord" id="2533279085403196" internalDescription="VENON &gt; MGOUL" name="Venoge nord &gt; Mont-Goulin" to="Mont-Goulin"/>
            <journey from="Mont-Goulin" id="2533279085403198" internalDescription="MGOUL &gt; VENON" name="Mont-Goulin &gt; Venoge nord" to="Venoge nord"/>
        </line>
    </station>
    <station name="Villars-St-Croix">
        <line description="Crissier-Centre - Mex Richardaz" id="11821953316814872" name="56">
            <journey from="Crissier-Centre" id="2533279085376941" internalDescription="CRISS &gt; RICHA" name="Crissier-Centre &gt; Richardaz" to="Richardaz"/>
            <journey from="Richardaz" id="2533279085376942" internalDescription="RICHA &gt; CRISS" name="Richardaz &gt; Crissier-Centre" to="Crissier-Centre"/>
        </line>
    </station>
    <station name="Vinet">
        <line description="Maladière - Désert" id="11821953316814855" name="2">
            <journey from="Maladière-Lac" id="2533279085378143" internalDescription="MALAD &gt; DST" name="Maladière-Lac &gt; Désert" to="Désert"/>
            <journey from="Désert" id="2533279085378157" internalDescription="DST &gt; MALAD" name="Désert &gt; Maladière-Lac" to="Maladière-Lac"/>
        </line>
    </station>
    <station name="Virgile-Rossel">
        <line description="Maladière - Sallaz" id="11821953316814873" name="6">
            <journey from="Maladière" id="2533279085378354" internalDescription="MALAD &gt; VALMT" name="Maladière &gt; Valmont" to="Valmont"/>
            <journey from="Valmont" id="2533279085378368" internalDescription="VALMT &gt; MALAD" name="Valmont &gt; Maladière" to="Maladière"/>
        </line>
    </station>
    <station name="Vivarium">
        <line description="Montbenon - Grand Vennes" id="11821953316814852" name="16">
            <journey from="Montbenon" id="2533279085363278" internalDescription="MBNON &gt; GVENN" name="Montbenon &gt; Grand Vennes" to="Grand Vennes"/>
            <journey from="Grand Vennes" id="2533279085363286" internalDescription="GVENN &gt; MBNON" name="Grand Vennes &gt; Montbenon" to="Montbenon"/>
        </line>
    </station>
    <station name="Voisinand">
        <line description="Lutry-Corniche - Prilly-Eglise" id="11821953316814886" name="9">
            <journey from="Lutry-Corniche" id="2533279085378570" internalDescription="LUTRY &gt; PRY" name="Lutry-Corniche &gt; Prilly-Eglise" to="Prilly-Eglise"/>
            <journey from="Prilly-Eglise" id="2533279085378585" internalDescription="PRY &gt; LUTRY" name="Prilly-Eglise &gt; Lutry-Corniche" to="Lutry-Corniche"/>
        </line>
    </station>
    <station name="Vucherens">
        <line description="Croisettes - Moudon-Gare" id="11821953316814875" name="62">
            <journey from="Croisettes" id="2533279085363696" internalDescription="CROIS &gt; MOUD" name="Croisettes &gt; Moudon-Gare" to="Moudon-Gare"/>
            <journey from="Moudon-Gare" id="2533279085379036" internalDescription="MOUD &gt; CROIS" name="Moudon-Gare &gt; Croisettes" to="Croisettes"/>
        </line>
    </station>
    <station name="Vulliemin">
        <line description="Montbenon - Grand Vennes" id="11821953316814852" name="16">
            <journey from="Montbenon" id="2533279085363278" internalDescription="MBNON &gt; GVENN" name="Montbenon &gt; Grand Vennes" to="Grand Vennes"/>
        </line>
    </station>
    <station name="Vulliens">
        <line description="Croisettes - Moudon-Gare" id="11821953316814875" name="62">
            <journey from="Croisettes" id="2533279085363696" internalDescription="CROIS &gt; MOUD" name="Croisettes &gt; Moudon-Gare" to="Moudon-Gare"/>
            <journey from="Moudon-Gare" id="2533279085379036" internalDescription="MOUD &gt; CROIS" name="Moudon-Gare &gt; Croisettes" to="Croisettes"/>
        </line>
    </station>
    <station name="Vulliette">
        <line description="Bois Murat - Chalet-à-Gobet" id="11821953316814868" name="45">
            <journey from="Bois Murat" id="2533279085370572" internalDescription="BMURA &gt; CHT" name="Bois Murat &gt; Chalet-à-Gobet" to="Chalet-à-Gobet"/>
            <journey from="Chalet-à-Gobet" id="2533279085370573" internalDescription="CHT &gt; BMURA" name="Chalet-à-Gobet &gt; Bois Murat" to="Bois Murat"/>
        </line>
    </station>
</stations>
